[{"player":"Cody Davis","playerLink":"/cfb/players/cody-davis-1.html","school_name":"Texas Tech","school_nameLink":"/cfb/schools/texas-tech/2012.html","tackles_solo":"7","tackles_assists":"4","tackles_total":"11","tackles_loss":"0.0","sacks":"0.0","def_int":"1","def_int_yds":"0","def_int_yds_per_int":"0.0","def_int_td":"0","pass_defended":"2","fumbles_rec":"","fumbles_rec_yds":"","fumbles_rec_td":"","fumbles_forced":""},{"player":"D.J. Johnson","playerLink":"/cfb/players/dj-johnson-2.html","school_name":"Texas Tech","school_nameLink":"/cfb/schools/texas-tech/2012.html","tackles_solo":"4","tackles_assists":"4","tackles_total":"8","tackles_loss":"0.0","sacks":"0.0","def_int":"1","def_int_yds":"15","def_int_yds_per_int":"15.0","def_int_td":"0","pass_defended":"2","fumbles_rec":"","fumbles_rec_yds":"","fumbles_rec_td":"","fumbles_forced":""},{"player":"Eugene Neboh","playerLink":"/cfb/players/eugene-neboh-1.html","school_name":"Texas Tech","school_nameLink":"/cfb/schools/texas-tech/2012.html","tackles_solo":"6","tackles_assists":"1","tackles_total":"7","tackles_loss":"0.0","sacks":"0.0","def_int":"","def_int_yds":"","def_int_yds_per_int":"","def_int_td":"","pass_defended":"","fumbles_rec":"","fumbles_rec_yds":"","fumbles_rec_td":"","fumbles_forced":""},{"player":"Will Smith","playerLink":"/cfb/players/will-smith-4.html","school_name":"Texas Tech","school_nameLink":"/cfb/schools/texas-tech/2012.html","tackles_solo":"5","tackles_assists":"1","tackles_total":"6","tackles_loss":"0.0","sacks":"0.0","def_int":"","def_int_yds":"","def_int_yds_per_int":"","def_int_td":"","pass_defended":"","fumbles_rec":"","fumbles_rec_yds":"","fumbles_rec_td":"","fumbles_forced":""},{"player":"Dartwan Bush","playerLink":"/cfb/players/dartwan-bush-1.html","school_name":"Texas Tech","school_nameLink":"/cfb/schools/texas-tech/2012.html","tackles_solo":"4","tackles_assists":"1","tackles_total":"5","tackles_loss":"1.0","sacks":"1.0","def_int":"","def_int_yds":"","def_int_yds_per_int":"","def_int_td":"","pass_defended":"","fumbles_rec":"","fumbles_rec_yds":"","fumbles_rec_td":"","fumbles_forced":""},{"player":"Kerry Hyder","playerLink":"/cfb/players/kerry-hyder-1.html","school_name":"Texas Tech","school_nameLink":"/cfb/schools/texas-tech/2012.html","tackles_solo":"4","tackles_assists":"1","tackles_total":"5","tackles_loss":"2.5","sacks":"1.0","def_int":"","def_int_yds":"","def_int_yds_per_int":"","def_int_td":"","pass_defended":"","fumbles_rec":"","fumbles_rec_yds":"","fumbles_rec_td":"","fumbles_forced":""},{"player":"Bruce Jones","playerLink":"/cfb/players/bruce-jones-1.html","school_name":"Texas Tech","school_nameLink":"/cfb/schools/texas-tech/2012.html","tackles_solo":"4","tackles_assists":"1","tackles_total":"5","tackles_loss":"0.0","sacks":"0.0","def_int":"","def_int_yds":"","def_int_yds_per_int":"","def_int_td":"","pass_defended":"","fumbles_rec":"","fumbles_rec_yds":"","fumbles_rec_td":"","fumbles_forced":""},{"player":"Sam Eguavoen","playerLink":"/cfb/players/sam-eguavoen-1.html","school_name":"Texas Tech","school_nameLink":"/cfb/schools/texas-tech/2012.html","tackles_solo":"2","tackles_assists":"2","tackles_total":"4","tackles_loss":"0.0","sacks":"0.0","def_int":"","def_int_yds":"","def_int_yds_per_int":"","def_int_td":"","pass_defended":"","fumbles_rec":"","fumbles_rec_yds":"","fumbles_rec_td":"","fumbles_forced":""},{"player":"Jarvis Phillips","playerLink":"/cfb/players/jarvis-phillips-1.html","school_name":"Texas Tech","school_nameLink":"/cfb/schools/texas-tech/2012.html","tackles_solo":"4","tackles_assists":"0","tackles_total":"4","tackles_loss":"0.0","sacks":"0.0","def_int":"","def_int_yds":"","def_int_yds_per_int":"","def_int_td":"","pass_defended":"","fumbles_rec":"","fumbles_rec_yds":"","fumbles_rec_td":"","fumbles_forced":""},{"player":"Tre' Porter","playerLink":"/cfb/players/tre-porter-1.html","school_name":"Texas Tech","school_nameLink":"/cfb/schools/texas-tech/2012.html","tackles_solo":"2","tackles_assists":"2","tackles_total":"4","tackles_loss":"0.0","sacks":"0.0","def_int":"","def_int_yds":"","def_int_yds_per_int":"","def_int_td":"","pass_defended":"","fumbles_rec":"","fumbles_rec_yds":"","fumbles_rec_td":"","fumbles_forced":""},{"player":"Delvon Simmons","playerLink":"/cfb/players/delvon-simmons-1.html","school_name":"Texas Tech","school_nameLink":"/cfb/schools/texas-tech/2012.html","tackles_solo":"1","tackles_assists":"3","tackles_total":"4","tackles_loss":"1.5","sacks":"0.0","def_int":"","def_int_yds":"","def_int_yds_per_int":"","def_int_td":"","pass_defended":"1","fumbles_rec":"","fumbles_rec_yds":"","fumbles_rec_td":"","fumbles_forced":""},{"player":"Micah Awe","playerLink":"/cfb/players/micah-awe-1.html","school_name":"Texas Tech","school_nameLink":"/cfb/schools/texas-tech/2012.html","tackles_solo":"2","tackles_assists":"0","tackles_total":"2","tackles_loss":"0.0","sacks":"0.0","def_int":"","def_int_yds":"","def_int_yds_per_int":"","def_int_td":"","pass_defended":"","fumbles_rec":"","fumbles_rec_yds":"","fumbles_rec_td":"","fumbles_forced":""},{"player":"Terrance Bullitt","playerLink":"/cfb/players/terrance-bullitt-1.html","school_name":"Texas Tech","school_nameLink":"/cfb/schools/texas-tech/2012.html","tackles_solo":"0","tackles_assists":"2","tackles_total":"2","tackles_loss":"0.0","sacks":"0.0","def_int":"","def_int_yds":"","def_int_yds_per_int":"","def_int_td":"","pass_defended":"","fumbles_rec":"","fumbles_rec_yds":"","fumbles_rec_td":"","fumbles_forced":""},{"player":"Blake Dees","playerLink":"/cfb/players/blake-dees-1.html","school_name":"Texas Tech","school_nameLink":"/cfb/schools/texas-tech/2012.html","tackles_solo":"1","tackles_assists":"1","tackles_total":"2","tackles_loss":"0.0","sacks":"0.0","def_int":"","def_int_yds":"","def_int_yds_per_int":"","def_int_td":"","pass_defended":"","fumbles_rec":"","fumbles_rec_yds":"","fumbles_rec_td":"","fumbles_forced":""},{"player":"Olaoluwa Falemi","playerLink":"/cfb/players/olaoluwa-falemi-1.html","school_name":"Texas Tech","school_nameLink":"/cfb/schools/texas-tech/2012.html","tackles_solo":"2","tackles_assists":"0","tackles_total":"2","tackles_loss":"0.0","sacks":"0.0","def_int":"","def_int_yds":"","def_int_yds_per_int":"","def_int_td":"","pass_defended":"","fumbles_rec":"","fumbles_rec_yds":"","fumbles_rec_td":"","fumbles_forced":""},{"player":"Branden Jackson","playerLink":"/cfb/players/branden-jackson-1.html","school_name":"Texas Tech","school_nameLink":"/cfb/schools/texas-tech/2012.html","tackles_solo":"1","tackles_assists":"1","tackles_total":"2","tackles_loss":"0.0","sacks":"0.0","def_int":"","def_int_yds":"","def_int_yds_per_int":"","def_int_td":"","pass_defended":"","fumbles_rec":"","fumbles_rec_yds":"","fumbles_rec_td":"","fumbles_forced":""},{"player":"Jackson Richards","playerLink":"/cfb/players/jackson-richards-1.html","school_name":"Texas Tech","school_nameLink":"/cfb/schools/texas-tech/2012.html","tackles_solo":"2","tackles_assists":"0","tackles_total":"2","tackles_loss":"0.0","sacks":"0.0","def_int":"","def_int_yds":"","def_int_yds_per_int":"","def_int_td":"","pass_defended":"","fumbles_rec":"","fumbles_rec_yds":"","fumbles_rec_td":"","fumbles_forced":""},{"player":"Pete Robertson","playerLink":"/cfb/players/pete-robertson-1.html","school_name":"Texas Tech","school_nameLink":"/cfb/schools/texas-tech/2012.html","tackles_solo":"2","tackles_assists":"0","tackles_total":"2","tackles_loss":"0.0","sacks":"0.0","def_int":"","def_int_yds":"","def_int_yds_per_int":"","def_int_td":"","pass_defended":"","fumbles_rec":"","fumbles_rec_yds":"","fumbles_rec_td":"","fumbles_forced":""},{"player":"Dennell Wesley","playerLink":"/cfb/players/dennell-wesley-1.html","school_name":"Texas Tech","school_nameLink":"/cfb/schools/texas-tech/2012.html","tackles_solo":"2","tackles_assists":"0","tackles_total":"2","tackles_loss":"1.0","sacks":"0.0","def_int":"","def_int_yds":"","def_int_yds_per_int":"","def_int_td":"","pass_defended":"","fumbles_rec":"","fumbles_rec_yds":"","fumbles_rec_td":"","fumbles_forced":""},{"player":"J.J. Gaines","playerLink":"/cfb/players/jj-gaines-1.html","school_name":"Texas Tech","school_nameLink":"/cfb/schools/texas-tech/2012.html","tackles_solo":"1","tackles_assists":"0","tackles_total":"1","tackles_loss":"0.0","sacks":"0.0","def_int":"","def_int_yds":"","def_int_yds_per_int":"","def_int_td":"","pass_defended":"","fumbles_rec":"","fumbles_rec_yds":"","fumbles_rec_td":"","fumbles_forced":""},{"header_tackles":"Tackles","header_def_int":"Def Int","header_fumbles":"Fumbles"},{"player":"Player","school_name":"School","tackles_solo":"Solo","tackles_assists":"Ast","tackles_total":"Tot","tackles_loss":"Loss","sacks":"Sk","def_int":"Int","def_int_yds":"Yds","def_int_yds_per_int":"Avg","def_int_td":"TD","pass_defended":"PD","fumbles_rec":"FR","fumbles_rec_yds":"Yds","fumbles_rec_td":"TD","fumbles_forced":"FF"},{"player":"Jason Verrett","playerLink":"/cfb/players/jason-verrett-1.html","school_name":"TCU","school_nameLink":"/cfb/schools/texas-christian/2012.html","tackles_solo":"9","tackles_assists":"2","tackles_total":"11","tackles_loss":"2.0","sacks":"0.0","def_int":"","def_int_yds":"","def_int_yds_per_int":"","def_int_td":"","pass_defended":"3","fumbles_rec":"","fumbles_rec_yds":"","fumbles_rec_td":"","fumbles_forced":""},{"player":"Joel Hasley","playerLink":"/cfb/players/joel-hasley-1.html","school_name":"TCU","school_nameLink":"/cfb/schools/texas-christian/2012.html","tackles_solo":"4","tackles_assists":"5","tackles_total":"9","tackles_loss":"3.0","sacks":"0.0","def_int":"","def_int_yds":"","def_int_yds_per_int":"","def_int_td":"","pass_defended":"","fumbles_rec":"","fumbles_rec_yds":"","fumbles_rec_td":"","fumbles_forced":""},{"player":"Chris Hackett","playerLink":"/cfb/players/chris-hackett-1.html","school_name":"TCU","school_nameLink":"/cfb/schools/texas-christian/2012.html","tackles_solo":"4","tackles_assists":"3","tackles_total":"7","tackles_loss":"0.0","sacks":"0.0","def_int":"","def_int_yds":"","def_int_yds_per_int":"","def_int_td":"","pass_defended":"","fumbles_rec":"","fumbles_rec_yds":"","fumbles_rec_td":"","fumbles_forced":""},{"player":"Elisha Olabode","playerLink":"/cfb/players/elisha-olabode-1.html","school_name":"TCU","school_nameLink":"/cfb/schools/texas-christian/2012.html","tackles_solo":"3","tackles_assists":"2","tackles_total":"5","tackles_loss":"0.0","sacks":"0.0","def_int":"","def_int_yds":"","def_int_yds_per_int":"","def_int_td":"","pass_defended":"","fumbles_rec":"","fumbles_rec_yds":"","fumbles_rec_td":"","fumbles_forced":""},{"player":"Kenny Cain","playerLink":"/cfb/players/kenny-cain-1.html","school_name":"TCU","school_nameLink":"/cfb/schools/texas-christian/2012.html","tackles_solo":"1","tackles_assists":"3","tackles_total":"4","tackles_loss":"0.0","sacks":"0.0","def_int":"","def_int_yds":"","def_int_yds_per_int":"","def_int_td":"","pass_defended":"","fumbles_rec":"","fumbles_rec_yds":"","fumbles_rec_td":"","fumbles_forced":""},{"player":"Devonte Fields","playerLink":"/cfb/players/devonte-fields-1.html","school_name":"TCU","school_nameLink":"/cfb/schools/texas-christian/2012.html","tackles_solo":"3","tackles_assists":"1","tackles_total":"4","tackles_loss":"2.5","sacks":"1.5","def_int":"","def_int_yds":"","def_int_yds_per_int":"","def_int_td":"","pass_defended":"1","fumbles_rec":"","fumbles_rec_yds":"","fumbles_rec_td":"","fumbles_forced":""},{"player":"Chucky Hunter","playerLink":"/cfb/players/chucky-hunter-1.html","school_name":"TCU","school_nameLink":"/cfb/schools/texas-christian/2012.html","tackles_solo":"1","tackles_assists":"3","tackles_total":"4","tackles_loss":"0.0","sacks":"0.0","def_int":"","def_int_yds":"","def_int_yds_per_int":"","def_int_td":"","pass_defended":"","fumbles_rec":"","fumbles_rec_yds":"","fumbles_rec_td":"","fumbles_forced":""},{"player":"Jonathan Anderson","playerLink":"/cfb/players/jonathan-anderson-1.html","school_name":"TCU","school_nameLink":"/cfb/schools/texas-christian/2012.html","tackles_solo":"3","tackles_assists":"0","tackles_total":"3","tackles_loss":"0.0","sacks":"0.0","def_int":"","def_int_yds":"","def_int_yds_per_int":"","def_int_td":"","pass_defended":"","fumbles_rec":"","fumbles_rec_yds":"","fumbles_rec_td":"","fumbles_forced":""},{"player":"Davion Pierson","playerLink":"/cfb/players/davion-pierson-1.html","school_name":"TCU","school_nameLink":"/cfb/schools/texas-christian/2012.html","tackles_solo":"1","tackles_assists":"2","tackles_total":"3","tackles_loss":"1.0","sacks":"1.0","def_int":"","def_int_yds":"","def_int_yds_per_int":"","def_int_td":"","pass_defended":"","fumbles_rec":"","fumbles_rec_yds":"","fumbles_rec_td":"","fumbles_forced":""},{"player":"Josh Carraway","playerLink":"/cfb/players/josh-carraway-1.html","school_name":"TCU","school_nameLink":"/cfb/schools/texas-christian/2012.html","tackles_solo":"1","tackles_assists":"0","tackles_total":"1","tackles_loss":"0.0","sacks":"0.0","def_int":"","def_int_yds":"","def_int_yds_per_int":"","def_int_td":"","pass_defended":"","fumbles_rec":"","fumbles_rec_yds":"","fumbles_rec_td":"","fumbles_forced":""},{"player":"Sam Carter","playerLink":"/cfb/players/sam-carter-1.html","school_name":"TCU","school_nameLink":"/cfb/schools/texas-christian/2012.html","tackles_solo":"0","tackles_assists":"1","tackles_total":"1","tackles_loss":"0.0","sacks":"0.0","def_int":"","def_int_yds":"","def_int_yds_per_int":"","def_int_td":"","pass_defended":"1","fumbles_rec":"","fumbles_rec_yds":"","fumbles_rec_td":"","fumbles_forced":""},{"player":"Aundre Dean","playerLink":"/cfb/players/aundre-dean-1.html","school_name":"TCU","school_nameLink":"/cfb/schools/texas-christian/2012.html","tackles_solo":"1","tackles_assists":"0","tackles_total":"1","tackles_loss":"0.0","sacks":"0.0","def_int":"","def_int_yds":"","def_int_yds_per_int":"","def_int_td":"","pass_defended":"","fumbles_rec":"","fumbles_rec_yds":"","fumbles_rec_td":"","fumbles_forced":""},{"player":"Deante' Gray","playerLink":"/cfb/players/deante-gray-1.html","school_name":"TCU","school_nameLink":"/cfb/schools/texas-christian/2012.html","tackles_solo":"1","tackles_assists":"0","tackles_total":"1","tackles_loss":"0.0","sacks":"0.0","def_int":"","def_int_yds":"","def_int_yds_per_int":"","def_int_td":"","pass_defended":"","fumbles_rec":"","fumbles_rec_yds":"","fumbles_rec_td":"","fumbles_forced":""},{"player":"Geoff Hooker","playerLink":"/cfb/players/geoff-hooker-1.html","school_name":"TCU","school_nameLink":"/cfb/schools/texas-christian/2012.html","tackles_solo":"1","tackles_assists":"0","tackles_total":"1","tackles_loss":"0.0","sacks":"0.0","def_int":"","def_int_yds":"","def_int_yds_per_int":"","def_int_td":"","pass_defended":"","fumbles_rec":"","fumbles_rec_yds":"","fumbles_rec_td":"","fumbles_forced":""},{"player":"Jon Koontz","playerLink":"/cfb/players/jon-koontz-1.html","school_name":"TCU","school_nameLink":"/cfb/schools/texas-christian/2012.html","tackles_solo":"0","tackles_assists":"1","tackles_total":"1","tackles_loss":"0.0","sacks":"0.0","def_int":"","def_int_yds":"","def_int_yds_per_int":"","def_int_td":"","pass_defended":"","fumbles_rec":"","fumbles_rec_yds":"","fumbles_rec_td":"","fumbles_forced":""},{"player":"Jon Lewis","playerLink":"/cfb/players/jon-lewis-1.html","school_name":"TCU","school_nameLink":"/cfb/schools/texas-christian/2012.html","tackles_solo":"1","tackles_assists":"0","tackles_total":"1","tackles_loss":"1.0","sacks":"0.0","def_int":"","def_int_yds":"","def_int_yds_per_int":"","def_int_td":"","pass_defended":"","fumbles_rec":"","fumbles_rec_yds":"","fumbles_rec_td":"","fumbles_forced":""},{"player":"James McFarland","playerLink":"/cfb/players/james-mcfarland-1.html","school_name":"TCU","school_nameLink":"/cfb/schools/texas-christian/2012.html","tackles_solo":"0","tackles_assists":"1","tackles_total":"1","tackles_loss":"0.5","sacks":"0.5","def_int":"","def_int_yds":"","def_int_yds_per_int":"","def_int_td":"","pass_defended":"","fumbles_rec":"","fumbles_rec_yds":"","fumbles_rec_td":"","fumbles_forced":""},{"player":"Kevin White","playerLink":"/cfb/players/kevin-white-5.html","school_name":"TCU","school_nameLink":"/cfb/schools/texas-christian/2012.html","tackles_solo":"1","tackles_assists":"0","tackles_total":"1","tackles_loss":"0.0","sacks":"0.0","def_int":"","def_int_yds":"","def_int_yds_per_int":"","def_int_td":"","pass_defended":"1","fumbles_rec":"","fumbles_rec_yds":"","fumbles_rec_td":"","fumbles_forced":""}]