[{"split_id":"Offense","g":"10","pass_cmp":"23.4","pass_att":"40.7","pass_cmp_pct":"57.5","pass_yds":"276.5","pass_td":"2.3","rush_att":"41.1","rush_yds":"171.7","rush_yds_per_att":"4.2","rush_td":"1.4"},{"split_id":"Defense","g":"10","opp_pass_cmp":"21.5","opp_pass_att":"41.2","opp_pass_cmp_pct":"52.2","opp_pass_yds":"272.2","opp_pass_td":"1.0","opp_rush_att":"40.0","opp_rush_yds":"131.3","opp_rush_yds_per_att":"3.3","opp_rush_td":"1.4"},{"split_id":"Difference","g":"","pass_cmp":"+1.9","pass_att":"-0.5","pass_cmp_pct":"+5.3","pass_yds":"+4.3","pass_td":"+1.3","rush_att":"+1.1","rush_yds":"+40.4","rush_yds_per_att":"+0.9","rush_td":"0.0"}]