[{"player":"Nathan Ricketts","playerLink":"/cfb/players/nathan-ricketts-1.html","school_name":"Central Michigan","school_nameLink":"/cfb/schools/central-michigan/2016.html","tackles_solo":"6","tackles_assists":"0","tackles_total":"6","tackles_loss":"2.0","sacks":"0.0","def_int":"","def_int_yds":"","def_int_yds_per_int":"","def_int_td":"","pass_defended":"1","fumbles_rec":"1","fumbles_rec_yds":"0","fumbles_rec_td":"0","fumbles_forced":"1"},{"player":"Alex Briones","playerLink":"/cfb/players/alex-briones-1.html","school_name":"Central Michigan","school_nameLink":"/cfb/schools/central-michigan/2016.html","tackles_solo":"4","tackles_assists":"1","tackles_total":"5","tackles_loss":"1.0","sacks":"0.0","def_int":"","def_int_yds":"","def_int_yds_per_int":"","def_int_td":"","pass_defended":"","fumbles_rec":"","fumbles_rec_yds":"","fumbles_rec_td":"","fumbles_forced":""},{"player":"Tony Annese","playerLink":"/cfb/players/tony-annese-1.html","school_name":"Central Michigan","school_nameLink":"/cfb/schools/central-michigan/2016.html","tackles_solo":"3","tackles_assists":"1","tackles_total":"4","tackles_loss":"0.0","sacks":"0.0","def_int":"","def_int_yds":"","def_int_yds_per_int":"","def_int_td":"","pass_defended":"1","fumbles_rec":"","fumbles_rec_yds":"","fumbles_rec_td":"","fumbles_forced":""},{"player":"Winslow Chapman","playerLink":"/cfb/players/winslow-chapman-1.html","school_name":"Central Michigan","school_nameLink":"/cfb/schools/central-michigan/2016.html","tackles_solo":"3","tackles_assists":"0","tackles_total":"3","tackles_loss":"0.0","sacks":"0.0","def_int":"1","def_int_yds":"0","def_int_yds_per_int":"0.0","def_int_td":"0","pass_defended":"0","fumbles_rec":"","fumbles_rec_yds":"","fumbles_rec_td":"","fumbles_forced":""},{"player":"Amari Coleman","playerLink":"/cfb/players/amari-coleman-1.html","school_name":"Central Michigan","school_nameLink":"/cfb/schools/central-michigan/2016.html","tackles_solo":"3","tackles_assists":"0","tackles_total":"3","tackles_loss":"1.0","sacks":"0.0","def_int":"1","def_int_yds":"27","def_int_yds_per_int":"27.0","def_int_td":"1","pass_defended":"0","fumbles_rec":"","fumbles_rec_yds":"","fumbles_rec_td":"","fumbles_forced":""},{"player":"Josh Cox","playerLink":"/cfb/players/josh-cox-1.html","school_name":"Central Michigan","school_nameLink":"/cfb/schools/central-michigan/2016.html","tackles_solo":"3","tackles_assists":"0","tackles_total":"3","tackles_loss":"0.0","sacks":"0.0","def_int":"","def_int_yds":"","def_int_yds_per_int":"","def_int_td":"","pass_defended":"1","fumbles_rec":"","fumbles_rec_yds":"","fumbles_rec_td":"","fumbles_forced":""},{"player":"Malik Fountain","playerLink":"/cfb/players/malik-fountain-1.html","school_name":"Central Michigan","school_nameLink":"/cfb/schools/central-michigan/2016.html","tackles_solo":"2","tackles_assists":"1","tackles_total":"3","tackles_loss":"1.0","sacks":"0.0","def_int":"","def_int_yds":"","def_int_yds_per_int":"","def_int_td":"","pass_defended":"","fumbles_rec":"","fumbles_rec_yds":"","fumbles_rec_td":"","fumbles_forced":""},{"player":"Sean Bunting","playerLink":"/cfb/players/sean-bunting-1.html","school_name":"Central Michigan","school_nameLink":"/cfb/schools/central-michigan/2016.html","tackles_solo":"2","tackles_assists":"0","tackles_total":"2","tackles_loss":"0.0","sacks":"0.0","def_int":"","def_int_yds":"","def_int_yds_per_int":"","def_int_td":"","pass_defended":"2","fumbles_rec":"","fumbles_rec_yds":"","fumbles_rec_td":"","fumbles_forced":""},{"player":"Mike Danna","playerLink":"/cfb/players/mike-danna-1.html","school_name":"Central Michigan","school_nameLink":"/cfb/schools/central-michigan/2016.html","tackles_solo":"2","tackles_assists":"0","tackles_total":"2","tackles_loss":"2.0","sacks":"1.0","def_int":"","def_int_yds":"","def_int_yds_per_int":"","def_int_td":"","pass_defended":"","fumbles_rec":"","fumbles_rec_yds":"","fumbles_rec_td":"","fumbles_forced":""},{"player":"Gary Jones","playerLink":"/cfb/players/gary-jones-1.html","school_name":"Central Michigan","school_nameLink":"/cfb/schools/central-michigan/2016.html","tackles_solo":"2","tackles_assists":"0","tackles_total":"2","tackles_loss":"0.0","sacks":"0.0","def_int":"","def_int_yds":"","def_int_yds_per_int":"","def_int_td":"","pass_defended":"","fumbles_rec":"","fumbles_rec_yds":"","fumbles_rec_td":"","fumbles_forced":""},{"player":"Donny Kyre","playerLink":"/cfb/players/donny-kyre-1.html","school_name":"Central Michigan","school_nameLink":"/cfb/schools/central-michigan/2016.html","tackles_solo":"2","tackles_assists":"0","tackles_total":"2","tackles_loss":"0.0","sacks":"0.0","def_int":"","def_int_yds":"","def_int_yds_per_int":"","def_int_td":"","pass_defended":"","fumbles_rec":"","fumbles_rec_yds":"","fumbles_rec_td":"","fumbles_forced":""},{"player":"Colton Odykirk","playerLink":"/cfb/players/colton-odykirk-1.html","school_name":"Central Michigan","school_nameLink":"/cfb/schools/central-michigan/2016.html","tackles_solo":"2","tackles_assists":"0","tackles_total":"2","tackles_loss":"0.0","sacks":"0.0","def_int":"","def_int_yds":"","def_int_yds_per_int":"","def_int_td":"","pass_defended":"","fumbles_rec":"","fumbles_rec_yds":"","fumbles_rec_td":"","fumbles_forced":""},{"player":"Joe Ostman","playerLink":"/cfb/players/joe-ostman-1.html","school_name":"Central Michigan","school_nameLink":"/cfb/schools/central-michigan/2016.html","tackles_solo":"1","tackles_assists":"1","tackles_total":"2","tackles_loss":"0.5","sacks":"0.5","def_int":"","def_int_yds":"","def_int_yds_per_int":"","def_int_td":"","pass_defended":"","fumbles_rec":"","fumbles_rec_yds":"","fumbles_rec_td":"","fumbles_forced":""},{"player":"Mitch Stanitzek","playerLink":"/cfb/players/mitch-stanitzek-1.html","school_name":"Central Michigan","school_nameLink":"/cfb/schools/central-michigan/2016.html","tackles_solo":"1","tackles_assists":"1","tackles_total":"2","tackles_loss":"0.5","sacks":"0.5","def_int":"","def_int_yds":"","def_int_yds_per_int":"","def_int_td":"","pass_defended":"","fumbles_rec":"","fumbles_rec_yds":"","fumbles_rec_td":"","fumbles_forced":""},{"player":"Trevor Apsey","playerLink":"/cfb/players/trevor-apsey-1.html","school_name":"Central Michigan","school_nameLink":"/cfb/schools/central-michigan/2016.html","tackles_solo":"1","tackles_assists":"0","tackles_total":"1","tackles_loss":"0.0","sacks":"0.0","def_int":"","def_int_yds":"","def_int_yds_per_int":"","def_int_td":"","pass_defended":"","fumbles_rec":"","fumbles_rec_yds":"","fumbles_rec_td":"","fumbles_forced":""},{"player":"Bobby Banks","playerLink":"/cfb/players/bobby-banks-1.html","school_name":"Central Michigan","school_nameLink":"/cfb/schools/central-michigan/2016.html","tackles_solo":"1","tackles_assists":"0","tackles_total":"1","tackles_loss":"0.0","sacks":"0.0","def_int":"","def_int_yds":"","def_int_yds_per_int":"","def_int_td":"","pass_defended":"","fumbles_rec":"","fumbles_rec_yds":"","fumbles_rec_td":"","fumbles_forced":""},{"player":"Carlos Clark","playerLink":"/cfb/players/carlos-clark-1.html","school_name":"Central Michigan","school_nameLink":"/cfb/schools/central-michigan/2016.html","tackles_solo":"1","tackles_assists":"0","tackles_total":"1","tackles_loss":"1.0","sacks":"0.0","def_int":"","def_int_yds":"","def_int_yds_per_int":"","def_int_td":"","pass_defended":"","fumbles_rec":"","fumbles_rec_yds":"","fumbles_rec_td":"","fumbles_forced":""},{"player":"D'Andre Dill","playerLink":"/cfb/players/dandre-dill-1.html","school_name":"Central Michigan","school_nameLink":"/cfb/schools/central-michigan/2016.html","tackles_solo":"1","tackles_assists":"0","tackles_total":"1","tackles_loss":"1.0","sacks":"0.0","def_int":"","def_int_yds":"","def_int_yds_per_int":"","def_int_td":"","pass_defended":"","fumbles_rec":"","fumbles_rec_yds":"","fumbles_rec_td":"","fumbles_forced":""},{"player":"Jahray Hayes","playerLink":"/cfb/players/jahray-hayes-1.html","school_name":"Central Michigan","school_nameLink":"/cfb/schools/central-michigan/2016.html","tackles_solo":"1","tackles_assists":"0","tackles_total":"1","tackles_loss":"0.0","sacks":"0.0","def_int":"","def_int_yds":"","def_int_yds_per_int":"","def_int_td":"","pass_defended":"","fumbles_rec":"","fumbles_rec_yds":"","fumbles_rec_td":"","fumbles_forced":""},{"player":"Otis Kearney","playerLink":"/cfb/players/otis-kearney-1.html","school_name":"Central Michigan","school_nameLink":"/cfb/schools/central-michigan/2016.html","tackles_solo":"0","tackles_assists":"1","tackles_total":"1","tackles_loss":"0.0","sacks":"0.0","def_int":"","def_int_yds":"","def_int_yds_per_int":"","def_int_td":"","pass_defended":"","fumbles_rec":"","fumbles_rec_yds":"","fumbles_rec_td":"","fumbles_forced":""},{"player":"Michael Oliver","playerLink":"/cfb/players/michael-oliver-1.html","school_name":"Central Michigan","school_nameLink":"/cfb/schools/central-michigan/2016.html","tackles_solo":"1","tackles_assists":"0","tackles_total":"1","tackles_loss":"0.0","sacks":"0.0","def_int":"","def_int_yds":"","def_int_yds_per_int":"","def_int_td":"","pass_defended":"","fumbles_rec":"","fumbles_rec_yds":"","fumbles_rec_td":"","fumbles_forced":""},{"player":"Jeff Perry","playerLink":"/cfb/players/jeff-perry-3.html","school_name":"Central Michigan","school_nameLink":"/cfb/schools/central-michigan/2016.html","tackles_solo":"1","tackles_assists":"0","tackles_total":"1","tackles_loss":"0.0","sacks":"0.0","def_int":"","def_int_yds":"","def_int_yds_per_int":"","def_int_td":"","pass_defended":"","fumbles_rec":"","fumbles_rec_yds":"","fumbles_rec_td":"","fumbles_forced":""},{"player":"Anthony Scarcelli","playerLink":"/cfb/players/anthony-scarcelli-1.html","school_name":"Central Michigan","school_nameLink":"/cfb/schools/central-michigan/2016.html","tackles_solo":"1","tackles_assists":"0","tackles_total":"1","tackles_loss":"0.0","sacks":"0.0","def_int":"","def_int_yds":"","def_int_yds_per_int":"","def_int_td":"","pass_defended":"","fumbles_rec":"","fumbles_rec_yds":"","fumbles_rec_td":"","fumbles_forced":""},{"player":"Emmitt Thomas","playerLink":"/cfb/players/emmitt-thomas-1.html","school_name":"Central Michigan","school_nameLink":"/cfb/schools/central-michigan/2016.html","tackles_solo":"1","tackles_assists":"0","tackles_total":"1","tackles_loss":"0.0","sacks":"0.0","def_int":"","def_int_yds":"","def_int_yds_per_int":"","def_int_td":"","pass_defended":"","fumbles_rec":"","fumbles_rec_yds":"","fumbles_rec_td":"","fumbles_forced":""}]