[{"ranker":"1","player":"Wali Lundy","playerLink":"/cfb/players/wali-lundy-1.html","g":"12","td_rush":"17","td_rec":"","td_def_int":"","td_fumbles_rec":"","td_punt_ret":"","td_kick_ret":"","td_other":"","td_total":"17","xpm":"","fgm":"","two_pt_md":"","safety_md":"","points":"102"},{"ranker":"2","player":"Connor Hughes","playerLink":"/cfb/players/connor-hughes-1.html","g":"12","td_rush":"","td_rec":"","td_def_int":"","td_fumbles_rec":"","td_punt_ret":"","td_kick_ret":"","td_other":"","td_total":"","xpm":"42","fgm":"17","two_pt_md":"","safety_md":"","points":"93"},{"ranker":"3","player":"Alvin Pearman","playerLink":"/cfb/players/alvin-pearman-1.html","g":"12","td_rush":"10","td_rec":"1","td_def_int":"","td_fumbles_rec":"","td_punt_ret":"1","td_kick_ret":"","td_other":"","td_total":"12","xpm":"","fgm":"","two_pt_md":"","safety_md":"","points":"72"},{"ranker":"4","player":"Heath Miller","playerLink":"/cfb/players/heath-miller-1.html","g":"12","td_rush":"","td_rec":"5","td_def_int":"","td_fumbles_rec":"","td_punt_ret":"","td_kick_ret":"","td_other":"","td_total":"5","xpm":"","fgm":"","two_pt_md":"","safety_md":"","points":"30"},{"ranker":"5","player":"Marques Hagans","playerLink":"/cfb/players/marques-hagans-1.html","g":"12","td_rush":"4","td_rec":"","td_def_int":"","td_fumbles_rec":"","td_punt_ret":"","td_kick_ret":"","td_other":"","td_total":"4","xpm":"","fgm":"","two_pt_md":"","safety_md":"","points":"24"},{"ranker":"6","player":"Michael McGrew","playerLink":"/cfb/players/michael-mcgrew-1.html","g":"12","td_rush":"","td_rec":"2","td_def_int":"","td_fumbles_rec":"","td_punt_ret":"","td_kick_ret":"","td_other":"","td_total":"2","xpm":"","fgm":"","two_pt_md":"","safety_md":"","points":"12"},{"ranker":"7","player":"Brandon Isaiah","playerLink":"/cfb/players/brandon-isaiah-1.html","g":"12","td_rush":"1","td_rec":"","td_def_int":"","td_fumbles_rec":"","td_punt_ret":"","td_kick_ret":"","td_other":"","td_total":"1","xpm":"","fgm":"","two_pt_md":"","safety_md":"","points":"6"},{"ranker":"8","player":"Deyon Williams","playerLink":"/cfb/players/deyon-williams-1.html","g":"10","td_rush":"","td_rec":"1","td_def_int":"","td_fumbles_rec":"","td_punt_ret":"","td_kick_ret":"","td_other":"","td_total":"1","xpm":"","fgm":"","two_pt_md":"","safety_md":"","points":"6"},{"ranker":"9","player":"Jason Snelling","playerLink":"/cfb/players/jason-snelling-1.html","g":"7","td_rush":"1","td_rec":"","td_def_int":"","td_fumbles_rec":"","td_punt_ret":"","td_kick_ret":"","td_other":"","td_total":"1","xpm":"","fgm":"","two_pt_md":"","safety_md":"","points":"6"},{"ranker":"10","player":"Marquis Weeks","playerLink":"/cfb/players/marquis-weeks-1.html","g":"12","td_rush":"","td_rec":"","td_def_int":"","td_fumbles_rec":"","td_punt_ret":"","td_kick_ret":"1","td_other":"","td_total":"1","xpm":"","fgm":"","two_pt_md":"","safety_md":"","points":"6"},{"ranker":"11","player":"Michael Johnson","playerLink":"/cfb/players/michael-johnson-7.html","g":"12","td_rush":"1","td_rec":"","td_def_int":"","td_fumbles_rec":"","td_punt_ret":"","td_kick_ret":"","td_other":"","td_total":"1","xpm":"","fgm":"","two_pt_md":"","safety_md":"","points":"6"}]