[{"ranker":"1","player":"Sheldon Evans","playerLink":"/cfb/players/sheldon-evans-1.html","g":"9","kick_ret":"15","kick_ret_yds":"315","kick_ret_yds_per_ret":"21.0","kick_ret_td":"0","punt_ret":"","punt_ret_yds":"","punt_ret_yds_per_ret":"","punt_ret_td":""},{"ranker":"2","player":"Rasheen Ali","playerLink":"/cfb/players/rasheen-ali-1.html","g":"6","kick_ret":"4","kick_ret_yds":"76","kick_ret_yds_per_ret":"19.0","kick_ret_td":"0","punt_ret":"","punt_ret_yds":"","punt_ret_yds_per_ret":"","punt_ret_td":""},{"ranker":"3","player":"Brenden Knox","playerLink":"/cfb/players/brenden-knox-1.html","g":"10","kick_ret":"2","kick_ret_yds":"26","kick_ret_yds_per_ret":"13.0","kick_ret_td":"0","punt_ret":"","punt_ret_yds":"","punt_ret_yds_per_ret":"","punt_ret_td":""},{"ranker":"4","player":"Jeremy Smith","playerLink":"/cfb/players/jeremy-smith-8.html","g":"4","kick_ret":"1","kick_ret_yds":"0","kick_ret_yds_per_ret":"0.0","kick_ret_td":"0","punt_ret":"","punt_ret_yds":"","punt_ret_yds_per_ret":"","punt_ret_td":""},{"ranker":"5","player":"Talik Keaton","playerLink":"/cfb/players/talik-keaton-1.html","g":"8","kick_ret":"","kick_ret_yds":"","kick_ret_yds_per_ret":"","kick_ret_td":"","punt_ret":"14","punt_ret_yds":"95","punt_ret_yds_per_ret":"6.8","punt_ret_td":"0"},{"ranker":"6","player":"Artie Henry","playerLink":"/cfb/players/artie-henry-2.html","g":"8","kick_ret":"","kick_ret_yds":"","kick_ret_yds_per_ret":"","kick_ret_td":"","punt_ret":"5","punt_ret_yds":"60","punt_ret_yds_per_ret":"12.0","punt_ret_td":"0"},{"ranker":"7","player":"Artie Henry III","playerLink":"/cfb/players/artie-henry-iii-1.html","g":"6","kick_ret":"","kick_ret_yds":"","kick_ret_yds_per_ret":"","kick_ret_td":"","punt_ret":"5","punt_ret_yds":"60","punt_ret_yds_per_ret":"12.0","punt_ret_td":"0"},{"ranker":"8","player":"Broc Thompson","playerLink":"/cfb/players/broc-thompson-1.html","g":"4","kick_ret":"","kick_ret_yds":"","kick_ret_yds_per_ret":"","kick_ret_td":"","punt_ret":"1","punt_ret_yds":"13","punt_ret_yds_per_ret":"13.0","punt_ret_td":"0"},{"ranker":"9","player":"Steven Gilmore","playerLink":"/cfb/players/steven-gilmore-1.html","g":"10","kick_ret":"","kick_ret_yds":"","kick_ret_yds_per_ret":"","kick_ret_td":"","punt_ret":"1","punt_ret_yds":"7","punt_ret_yds_per_ret":"7.0","punt_ret_td":"0"}]