[{"quarter":"1","time":"10:48","team":"TULN","teamLink":"/cfb/schools/tulane/2017.html","description":"Terren Encalade 30 yard pass from Jonathan Banks (Coby Neenan kick)","descriptionLink":"/cfb/players/terren-encalade-1.html","vis_team_score":"0","home_team_score":"7"},{"quarter":"","time":"7:06","team":"TULN","teamLink":"/cfb/schools/tulane/2017.html","description":"Jonathan Banks 7 yard run (Coby Neenan kick)","descriptionLink":"/cfb/players/jonathan-banks-1.html","vis_team_score":"0","home_team_score":"14"},{"quarter":"2","time":"5:15","team":"TULN","teamLink":"/cfb/schools/tulane/2017.html","description":"Coby Neenan 21 yard field goal","descriptionLink":"/cfb/players/coby-neenan-1.html","vis_team_score":"0","home_team_score":"17"},{"quarter":"","time":"3:16","team":"TULN","teamLink":"/cfb/schools/tulane/2017.html","description":"Dontrell Hilliard 62 yard pass from Jonathan Banks (Coby Neenan kick)","descriptionLink":"/cfb/players/dontrell-hilliard-1.html","vis_team_score":"0","home_team_score":"24"},{"quarter":"3","time":"12:06","team":"TULN","teamLink":"/cfb/schools/tulane/2017.html","description":"Darnell Mooney 19 yard pass from Jonathan Banks (Coby Neenan kick)","descriptionLink":"/cfb/players/darnell-mooney-1.html","vis_team_score":"0","home_team_score":"31"},{"quarter":"","time":"5:25","team":"GRAM","description":"Martez Carter 5 yard run (Marc Orozco kick)","vis_team_score":"7","home_team_score":"31"},{"quarter":"4","time":"14:49","team":"TULN","teamLink":"/cfb/schools/tulane/2017.html","description":"Terren Encalade 58 yard run (kick failed)","descriptionLink":"/cfb/players/terren-encalade-1.html","vis_team_score":"7","home_team_score":"37"},{"quarter":"","time":"14:27","team":"GRAM","description":"Martez Carter 51 yard run (Marc Orozco kick)","vis_team_score":"14","home_team_score":"37"},{"quarter":"","time":"8:13","team":"TULN","teamLink":"/cfb/schools/tulane/2017.html","description":"Darius Bradwell 27 yard run (kick failed)","descriptionLink":"/cfb/players/darius-bradwell-1.html","vis_team_score":"14","home_team_score":"43"}]