[{"ranker":"1","player":"Justin Herbert","playerLink":"/cfb/players/justin-herbert-1.html","g":"13","pass_cmp":"240","pass_att":"404","pass_cmp_pct":"59.4","pass_yds":"3151","pass_yds_per_att":"7.8","adj_pass_yds_per_att":"8.3","pass_td":"29","pass_int":"8","pass_rating":"144.6"},{"ranker":"2","player":"Braxton Burmeister","playerLink":"/cfb/players/braxton-burmeister-1.html","g":"4","pass_cmp":"5","pass_att":"10","pass_cmp_pct":"50.0","pass_yds":"43","pass_yds_per_att":"4.3","adj_pass_yds_per_att":"4.3","pass_td":"0","pass_int":"0","pass_rating":"86.1"},{"ranker":"3","player":"Blake Maimone","playerLink":"/cfb/players/blake-maimone-1.html","g":"13","pass_cmp":"1","pass_att":"1","pass_cmp_pct":"100.0","pass_yds":"28","pass_yds_per_att":"28.0","adj_pass_yds_per_att":"28.0","pass_td":"0","pass_int":"0","pass_rating":"335.2"}]