[{"ranker":"1","player":"Deonce Whitaker","playerLink":"/cfb/players/deonce-whitaker-1.html","g":"9","rush_att":"137","rush_yds":"769","rush_yds_per_att":"5.6","rush_td":"10","rec":"16","rec_yds":"138","rec_yds_per_rec":"8.6","rec_td":"1","scrim_att":"153","scrim_yds":"907","scrim_yds_per_att":"5.9","scrim_td":"11"},{"ranker":"2","player":"Chris Kasteler","playerLink":"/cfb/players/chris-kasteler-1.html","g":"10","rush_att":"66","rush_yds":"-127","rush_yds_per_att":"-1.9","rush_td":"0","rec":"","rec_yds":"","rec_yds_per_rec":"","rec_td":"","scrim_att":"66","scrim_yds":"-127","scrim_yds_per_att":"-1.9","scrim_td":"0"},{"ranker":"3","player":"Darian Morton","playerLink":"/cfb/players/darian-morton-1.html","g":"5","rush_att":"32","rush_yds":"203","rush_yds_per_att":"6.3","rush_td":"1","rec":"1","rec_yds":"5","rec_yds_per_rec":"5.0","rec_td":"0","scrim_att":"33","scrim_yds":"208","scrim_yds_per_att":"6.3","scrim_td":"1"},{"ranker":"4","player":"Roger Ratliff","playerLink":"/cfb/players/roger-ratliff-1.html","g":"8","rush_att":"29","rush_yds":"116","rush_yds_per_att":"4.0","rush_td":"0","rec":"","rec_yds":"","rec_yds_per_rec":"","rec_td":"","scrim_att":"29","scrim_yds":"116","scrim_yds_per_att":"4.0","scrim_td":"0"},{"ranker":"5","player":"Casey Leblanc","playerLink":"/cfb/players/casey-leblanc-1.html","g":"10","rush_att":"27","rush_yds":"172","rush_yds_per_att":"6.4","rush_td":"3","rec":"35","rec_yds":"418","rec_yds_per_rec":"11.9","rec_td":"2","scrim_att":"62","scrim_yds":"590","scrim_yds_per_att":"9.5","scrim_td":"5"},{"ranker":"6","player":"Patrick Battle","playerLink":"/cfb/players/patrick-battle-1.html","g":"9","rush_att":"18","rush_yds":"51","rush_yds_per_att":"2.8","rush_td":"1","rec":"1","rec_yds":"5","rec_yds_per_rec":"5.0","rec_td":"0","scrim_att":"19","scrim_yds":"56","scrim_yds_per_att":"2.9","scrim_td":"1"},{"ranker":"7","player":"Brennan Crooks","playerLink":"/cfb/players/brennan-crooks-1.html","g":"9","rush_att":"17","rush_yds":"27","rush_yds_per_att":"1.6","rush_td":"0","rec":"","rec_yds":"","rec_yds_per_rec":"","rec_td":"","scrim_att":"17","scrim_yds":"27","scrim_yds_per_att":"1.6","scrim_td":"0"},{"ranker":"8","player":"Steven Pulley","playerLink":"/cfb/players/steven-pulley-1.html","g":"10","rush_att":"2","rush_yds":"-2","rush_yds_per_att":"-1.0","rush_td":"0","rec":"54","rec_yds":"772","rec_yds_per_rec":"14.3","rec_td":"5","scrim_att":"56","scrim_yds":"770","scrim_yds_per_att":"13.8","scrim_td":"5"},{"ranker":"9","player":"Waking Bailey","playerLink":"/cfb/players/waking-bailey-1.html","g":"10","rush_att":"","rush_yds":"","rush_yds_per_att":"","rush_td":"","rec":"35","rec_yds":"420","rec_yds_per_rec":"12.0","rec_td":"2","scrim_att":"35","scrim_yds":"420","scrim_yds_per_att":"12.0","scrim_td":"2"},{"ranker":"10","player":"Shawn Green","playerLink":"/cfb/players/shawn-green-1.html","g":"9","rush_att":"","rush_yds":"","rush_yds_per_att":"","rush_td":"","rec":"20","rec_yds":"273","rec_yds_per_rec":"13.7","rec_td":"0","scrim_att":"20","scrim_yds":"273","scrim_yds_per_att":"13.7","scrim_td":"0"},{"ranker":"11","player":"Sean Brewer","playerLink":"/cfb/players/sean-brewer-1.html","g":"9","rush_att":"","rush_yds":"","rush_yds_per_att":"","rush_td":"","rec":"20","rec_yds":"152","rec_yds_per_rec":"7.6","rec_td":"3","scrim_att":"20","scrim_yds":"152","scrim_yds_per_att":"7.6","scrim_td":"3"},{"ranker":"12","player":"Kenny Nears","playerLink":"/cfb/players/kenny-nears-1.html","g":"6","rush_att":"","rush_yds":"","rush_yds_per_att":"","rush_td":"","rec":"8","rec_yds":"83","rec_yds_per_rec":"10.4","rec_td":"1","scrim_att":"8","scrim_yds":"83","scrim_yds_per_att":"10.4","scrim_td":"1"},{"ranker":"13","player":"Eric Ruhle","playerLink":"/cfb/players/eric-ruhle-1.html","g":"2","rush_att":"","rush_yds":"","rush_yds_per_att":"","rush_td":"","rec":"7","rec_yds":"101","rec_yds_per_rec":"14.4","rec_td":"1","scrim_att":"7","scrim_yds":"101","scrim_yds_per_att":"14.4","scrim_td":"1"},{"ranker":"14","player":"An Troung","playerLink":"/cfb/players/an-troung-1.html","g":"3","rush_att":"","rush_yds":"","rush_yds_per_att":"","rush_td":"","rec":"4","rec_yds":"52","rec_yds_per_rec":"13.0","rec_td":"1","scrim_att":"4","scrim_yds":"52","scrim_yds_per_att":"13.0","scrim_td":"1"},{"ranker":"15","player":"Donte Scarbrough","playerLink":"/cfb/players/donte-scarbrough-1.html","g":"8","rush_att":"","rush_yds":"","rush_yds_per_att":"","rush_td":"","rec":"3","rec_yds":"24","rec_yds_per_rec":"8.0","rec_td":"0","scrim_att":"3","scrim_yds":"24","scrim_yds_per_att":"8.0","scrim_td":"0"},{"ranker":"16","player":"Elonte Vaughn","playerLink":"/cfb/players/elonte-vaughn-1.html","g":"5","rush_att":"","rush_yds":"","rush_yds_per_att":"","rush_td":"","rec":"2","rec_yds":"39","rec_yds_per_rec":"19.5","rec_td":"0","scrim_att":"2","scrim_yds":"39","scrim_yds_per_att":"19.5","scrim_td":"0"},{"ranker":"17","player":"Jarmar Julien","playerLink":"/cfb/players/jarmar-julien-1.html","g":"10","rush_att":"","rush_yds":"","rush_yds_per_att":"","rush_td":"","rec":"1","rec_yds":"8","rec_yds_per_rec":"8.0","rec_td":"0","scrim_att":"1","scrim_yds":"8","scrim_yds_per_att":"8.0","scrim_td":"0"}]