[{"split_id":"Offense","g":"11","pass_cmp":"19.0","pass_att":"38.7","pass_cmp_pct":"49.1","pass_yds":"243.3","pass_td":"0.7","rush_att":"36.7","rush_yds":"116.3","rush_yds_per_att":"3.2","rush_td":"1.5"},{"split_id":"Defense","g":"11","opp_pass_cmp":"17.5","opp_pass_att":"29.3","opp_pass_cmp_pct":"59.6","opp_pass_yds":"241.5","opp_pass_td":"1.5","opp_rush_att":"45.5","opp_rush_yds":"169.1","opp_rush_yds_per_att":"3.7","opp_rush_td":"2.4"},{"split_id":"Difference","g":"","pass_cmp":"+1.5","pass_att":"+9.4","pass_cmp_pct":"-10.5","pass_yds":"+1.8","pass_td":"-0.8","rush_att":"-8.8","rush_yds":"-52.8","rush_yds_per_att":"-0.5","rush_td":"-0.9"}]