[{"player":"Baylon Spector","playerLink":"/cfb/players/baylon-spector-1.html","school_name":"Clemson","school_nameLink":"/cfb/schools/clemson/2021.html","tackles_solo":"9","tackles_assists":"10","tackles_total":"19","tackles_loss":"0.0","sacks":"0.0","def_int":"","def_int_yds":"","def_int_yds_per_int":"","def_int_td":"","pass_defended":"1","fumbles_rec":"","fumbles_rec_yds":"","fumbles_rec_td":"","fumbles_forced":""},{"player":"R.J. Mickens","playerLink":"/cfb/players/rj-mickens-1.html","school_name":"Clemson","school_nameLink":"/cfb/schools/clemson/2021.html","tackles_solo":"2","tackles_assists":"8","tackles_total":"10","tackles_loss":"0.0","sacks":"0.0","def_int":"","def_int_yds":"","def_int_yds_per_int":"","def_int_td":"","pass_defended":"","fumbles_rec":"","fumbles_rec_yds":"","fumbles_rec_td":"","fumbles_forced":""},{"player":"Andrew Mukuba","playerLink":"/cfb/players/andrew-mukuba-1.html","school_name":"Clemson","school_nameLink":"/cfb/schools/clemson/2021.html","tackles_solo":"7","tackles_assists":"3","tackles_total":"10","tackles_loss":"1.0","sacks":"0.0","def_int":"","def_int_yds":"","def_int_yds_per_int":"","def_int_td":"","pass_defended":"","fumbles_rec":"","fumbles_rec_yds":"","fumbles_rec_td":"","fumbles_forced":""},{"player":"LaVonta Bentley","playerLink":"/cfb/players/lavonta-bentley-1.html","school_name":"Clemson","school_nameLink":"/cfb/schools/clemson/2021.html","tackles_solo":"4","tackles_assists":"5","tackles_total":"9","tackles_loss":"0.0","sacks":"0.0","def_int":"","def_int_yds":"","def_int_yds_per_int":"","def_int_td":"","pass_defended":"","fumbles_rec":"","fumbles_rec_yds":"","fumbles_rec_td":"","fumbles_forced":""},{"player":"Trenton Simpson","playerLink":"/cfb/players/trenton-simpson-1.html","school_name":"Clemson","school_nameLink":"/cfb/schools/clemson/2021.html","tackles_solo":"2","tackles_assists":"6","tackles_total":"8","tackles_loss":"0.0","sacks":"0.0","def_int":"","def_int_yds":"","def_int_yds_per_int":"","def_int_td":"","pass_defended":"1","fumbles_rec":"","fumbles_rec_yds":"","fumbles_rec_td":"","fumbles_forced":""},{"player":"Andrew Booth Jr.","playerLink":"/cfb/players/andrew-booth-jr-1.html","school_name":"Clemson","school_nameLink":"/cfb/schools/clemson/2021.html","tackles_solo":"4","tackles_assists":"2","tackles_total":"6","tackles_loss":"0.0","sacks":"0.0","def_int":"","def_int_yds":"","def_int_yds_per_int":"","def_int_td":"","pass_defended":"","fumbles_rec":"","fumbles_rec_yds":"","fumbles_rec_td":"","fumbles_forced":""},{"player":"Myles Murphy","playerLink":"/cfb/players/myles-murphy-1.html","school_name":"Clemson","school_nameLink":"/cfb/schools/clemson/2021.html","tackles_solo":"2","tackles_assists":"4","tackles_total":"6","tackles_loss":"1.0","sacks":"0.0","def_int":"","def_int_yds":"","def_int_yds_per_int":"","def_int_td":"","pass_defended":"","fumbles_rec":"","fumbles_rec_yds":"","fumbles_rec_td":"","fumbles_forced":""},{"player":"Xavier Thomas","playerLink":"/cfb/players/xavier-thomas-1.html","school_name":"Clemson","school_nameLink":"/cfb/schools/clemson/2021.html","tackles_solo":"3","tackles_assists":"2","tackles_total":"5","tackles_loss":"2.0","sacks":"2.0","def_int":"","def_int_yds":"","def_int_yds_per_int":"","def_int_td":"","pass_defended":"","fumbles_rec":"","fumbles_rec_yds":"","fumbles_rec_td":"","fumbles_forced":"1"},{"player":"Ruke Orhorhoro","playerLink":"/cfb/players/ruke-orhorhoro-1.html","school_name":"Clemson","school_nameLink":"/cfb/schools/clemson/2021.html","tackles_solo":"0","tackles_assists":"4","tackles_total":"4","tackles_loss":"0.0","sacks":"0.0","def_int":"","def_int_yds":"","def_int_yds_per_int":"","def_int_td":"","pass_defended":"","fumbles_rec":"1","fumbles_rec_yds":"0","fumbles_rec_td":"0","fumbles_forced":"0"},{"player":"James Skalski","playerLink":"/cfb/players/james-skalski-1.html","school_name":"Clemson","school_nameLink":"/cfb/schools/clemson/2021.html","tackles_solo":"0","tackles_assists":"4","tackles_total":"4","tackles_loss":"0.0","sacks":"0.0","def_int":"","def_int_yds":"","def_int_yds_per_int":"","def_int_td":"","pass_defended":"","fumbles_rec":"","fumbles_rec_yds":"","fumbles_rec_td":"","fumbles_forced":""},{"player":"Barrett Carter","playerLink":"/cfb/players/barrett-carter-1.html","school_name":"Clemson","school_nameLink":"/cfb/schools/clemson/2021.html","tackles_solo":"2","tackles_assists":"1","tackles_total":"3","tackles_loss":"0.0","sacks":"0.0","def_int":"","def_int_yds":"","def_int_yds_per_int":"","def_int_td":"","pass_defended":"","fumbles_rec":"","fumbles_rec_yds":"","fumbles_rec_td":"","fumbles_forced":""},{"player":"Etinosa Reuben","playerLink":"/cfb/players/etinosa-reuben-1.html","school_name":"Clemson","school_nameLink":"/cfb/schools/clemson/2021.html","tackles_solo":"0","tackles_assists":"3","tackles_total":"3","tackles_loss":"0.0","sacks":"0.0","def_int":"","def_int_yds":"","def_int_yds_per_int":"","def_int_td":"","pass_defended":"","fumbles_rec":"","fumbles_rec_yds":"","fumbles_rec_td":"","fumbles_forced":""},{"player":"Nolan Turner","playerLink":"/cfb/players/nolan-turner-1.html","school_name":"Clemson","school_nameLink":"/cfb/schools/clemson/2021.html","tackles_solo":"3","tackles_assists":"0","tackles_total":"3","tackles_loss":"1.0","sacks":"1.0","def_int":"","def_int_yds":"","def_int_yds_per_int":"","def_int_td":"","pass_defended":"","fumbles_rec":"","fumbles_rec_yds":"","fumbles_rec_td":"","fumbles_forced":""},{"player":"Justin Foster","playerLink":"/cfb/players/justin-foster-1.html","school_name":"Clemson","school_nameLink":"/cfb/schools/clemson/2021.html","tackles_solo":"1","tackles_assists":"1","tackles_total":"2","tackles_loss":"0.0","sacks":"0.0","def_int":"","def_int_yds":"","def_int_yds_per_int":"","def_int_td":"","pass_defended":"","fumbles_rec":"","fumbles_rec_yds":"","fumbles_rec_td":"","fumbles_forced":""},{"player":"Mario Goodrich","playerLink":"/cfb/players/mario-goodrich-1.html","school_name":"Clemson","school_nameLink":"/cfb/schools/clemson/2021.html","tackles_solo":"1","tackles_assists":"1","tackles_total":"2","tackles_loss":"0.0","sacks":"0.0","def_int":"","def_int_yds":"","def_int_yds_per_int":"","def_int_td":"","pass_defended":"","fumbles_rec":"","fumbles_rec_yds":"","fumbles_rec_td":"","fumbles_forced":""},{"player":"Justin Mascoll","playerLink":"/cfb/players/justin-mascoll-1.html","school_name":"Clemson","school_nameLink":"/cfb/schools/clemson/2021.html","tackles_solo":"0","tackles_assists":"2","tackles_total":"2","tackles_loss":"0.0","sacks":"0.0","def_int":"","def_int_yds":"","def_int_yds_per_int":"","def_int_td":"","pass_defended":"","fumbles_rec":"","fumbles_rec_yds":"","fumbles_rec_td":"","fumbles_forced":""},{"player":"Kane Patterson","playerLink":"/cfb/players/kane-patterson-1.html","school_name":"Clemson","school_nameLink":"/cfb/schools/clemson/2021.html","tackles_solo":"0","tackles_assists":"2","tackles_total":"2","tackles_loss":"0.0","sacks":"0.0","def_int":"","def_int_yds":"","def_int_yds_per_int":"","def_int_td":"","pass_defended":"","fumbles_rec":"","fumbles_rec_yds":"","fumbles_rec_td":"","fumbles_forced":""},{"player":"Tyler Venables","playerLink":"/cfb/players/tyler-venables-1.html","school_name":"Clemson","school_nameLink":"/cfb/schools/clemson/2021.html","tackles_solo":"1","tackles_assists":"1","tackles_total":"2","tackles_loss":"0.0","sacks":"0.0","def_int":"","def_int_yds":"","def_int_yds_per_int":"","def_int_td":"","pass_defended":"","fumbles_rec":"","fumbles_rec_yds":"","fumbles_rec_td":"","fumbles_forced":""},{"player":"Bryan Bresee","playerLink":"/cfb/players/bryan-bresee-1.html","school_name":"Clemson","school_nameLink":"/cfb/schools/clemson/2021.html","tackles_solo":"0","tackles_assists":"1","tackles_total":"1","tackles_loss":"0.0","sacks":"0.0","def_int":"","def_int_yds":"","def_int_yds_per_int":"","def_int_td":"","pass_defended":"","fumbles_rec":"","fumbles_rec_yds":"","fumbles_rec_td":"","fumbles_forced":""},{"player":"Joseph Charleston","playerLink":"/cfb/players/joseph-charleston-1.html","school_name":"Clemson","school_nameLink":"/cfb/schools/clemson/2021.html","tackles_solo":"0","tackles_assists":"1","tackles_total":"1","tackles_loss":"0.0","sacks":"0.0","def_int":"","def_int_yds":"","def_int_yds_per_int":"","def_int_td":"","pass_defended":"","fumbles_rec":"","fumbles_rec_yds":"","fumbles_rec_td":"","fumbles_forced":""},{"player":"K.J. Henry","playerLink":"/cfb/players/kj-henry-1.html","school_name":"Clemson","school_nameLink":"/cfb/schools/clemson/2021.html","tackles_solo":"1","tackles_assists":"0","tackles_total":"1","tackles_loss":"1.0","sacks":"0.0","def_int":"","def_int_yds":"","def_int_yds_per_int":"","def_int_td":"","pass_defended":"","fumbles_rec":"","fumbles_rec_yds":"","fumbles_rec_td":"","fumbles_forced":""},{"player":"Sheridan Jones","playerLink":"/cfb/players/sheridan-jones-1.html","school_name":"Clemson","school_nameLink":"/cfb/schools/clemson/2021.html","tackles_solo":"1","tackles_assists":"0","tackles_total":"1","tackles_loss":"0.0","sacks":"0.0","def_int":"","def_int_yds":"","def_int_yds_per_int":"","def_int_td":"","pass_defended":"","fumbles_rec":"","fumbles_rec_yds":"","fumbles_rec_td":"","fumbles_forced":""},{"player":"Jalyn Phillips","playerLink":"/cfb/players/jalyn-phillips-1.html","school_name":"Clemson","school_nameLink":"/cfb/schools/clemson/2021.html","tackles_solo":"1","tackles_assists":"0","tackles_total":"1","tackles_loss":"0.0","sacks":"0.0","def_int":"","def_int_yds":"","def_int_yds_per_int":"","def_int_td":"","pass_defended":"","fumbles_rec":"","fumbles_rec_yds":"","fumbles_rec_td":"","fumbles_forced":""},{"player":"E.J. Williams","playerLink":"/cfb/players/ej-williams-2.html","school_name":"Clemson","school_nameLink":"/cfb/schools/clemson/2021.html","tackles_solo":"1","tackles_assists":"0","tackles_total":"1","tackles_loss":"0.0","sacks":"0.0","def_int":"","def_int_yds":"","def_int_yds_per_int":"","def_int_td":"","pass_defended":"","fumbles_rec":"","fumbles_rec_yds":"","fumbles_rec_td":"","fumbles_forced":""},{"player":"Tre Williams","playerLink":"/cfb/players/tre-williams-4.html","school_name":"Clemson","school_nameLink":"/cfb/schools/clemson/2021.html","tackles_solo":"0","tackles_assists":"1","tackles_total":"1","tackles_loss":"0.0","sacks":"0.0","def_int":"","def_int_yds":"","def_int_yds_per_int":"","def_int_td":"","pass_defended":"","fumbles_rec":"","fumbles_rec_yds":"","fumbles_rec_td":"","fumbles_forced":""},{"header_tackles":"Tackles","header_def_int":"Def Int","header_fumbles":"Fumbles"},{"player":"Player","school_name":"School","tackles_solo":"Solo","tackles_assists":"Ast","tackles_total":"Tot","tackles_loss":"Loss","sacks":"Sk","def_int":"Int","def_int_yds":"Yds","def_int_yds_per_int":"Avg","def_int_td":"TD","pass_defended":"PD","fumbles_rec":"FR","fumbles_rec_yds":"Yds","fumbles_rec_td":"TD","fumbles_forced":"FF"},{"player":"Isaiah Moore","playerLink":"/cfb/players/isaiah-moore-1.html","school_name":"North Carolina State","school_nameLink":"/cfb/schools/north-carolina-state/2021.html","tackles_solo":"3","tackles_assists":"5","tackles_total":"8","tackles_loss":"2.0","sacks":"0.0","def_int":"","def_int_yds":"","def_int_yds_per_int":"","def_int_td":"","pass_defended":"1","fumbles_rec":"","fumbles_rec_yds":"","fumbles_rec_td":"","fumbles_forced":""},{"player":"Tanner Ingle","playerLink":"/cfb/players/tanner-ingle-1.html","school_name":"North Carolina State","school_nameLink":"/cfb/schools/north-carolina-state/2021.html","tackles_solo":"0","tackles_assists":"7","tackles_total":"7","tackles_loss":"0.5","sacks":"0.0","def_int":"","def_int_yds":"","def_int_yds_per_int":"","def_int_td":"","pass_defended":"1","fumbles_rec":"","fumbles_rec_yds":"","fumbles_rec_td":"","fumbles_forced":""},{"player":"Derrek Pitts","playerLink":"/cfb/players/derrek-pitts-1.html","school_name":"North Carolina State","school_nameLink":"/cfb/schools/north-carolina-state/2021.html","tackles_solo":"5","tackles_assists":"2","tackles_total":"7","tackles_loss":"0.5","sacks":"0.0","def_int":"","def_int_yds":"","def_int_yds_per_int":"","def_int_td":"","pass_defended":"","fumbles_rec":"","fumbles_rec_yds":"","fumbles_rec_td":"","fumbles_forced":""},{"player":"Cory Durden","playerLink":"/cfb/players/cory-durden-1.html","school_name":"North Carolina State","school_nameLink":"/cfb/schools/north-carolina-state/2021.html","tackles_solo":"1","tackles_assists":"5","tackles_total":"6","tackles_loss":"1.5","sacks":"1.5","def_int":"","def_int_yds":"","def_int_yds_per_int":"","def_int_td":"","pass_defended":"","fumbles_rec":"","fumbles_rec_yds":"","fumbles_rec_td":"","fumbles_forced":""},{"player":"Drake Thomas","playerLink":"/cfb/players/drake-thomas-2.html","school_name":"North Carolina State","school_nameLink":"/cfb/schools/north-carolina-state/2021.html","tackles_solo":"0","tackles_assists":"3","tackles_total":"3","tackles_loss":"0.0","sacks":"0.0","def_int":"1","def_int_yds":"0","def_int_yds_per_int":"0.0","def_int_td":"0","pass_defended":"0","fumbles_rec":"","fumbles_rec_yds":"","fumbles_rec_td":"","fumbles_forced":""},{"player":"Jakeen Harris","playerLink":"/cfb/players/jakeen-harris-1.html","school_name":"North Carolina State","school_nameLink":"/cfb/schools/north-carolina-state/2021.html","tackles_solo":"3","tackles_assists":"0","tackles_total":"3","tackles_loss":"0.0","sacks":"0.0","def_int":"","def_int_yds":"","def_int_yds_per_int":"","def_int_td":"","pass_defended":"","fumbles_rec":"","fumbles_rec_yds":"","fumbles_rec_td":"","fumbles_forced":""},{"player":"Jaylon Scott","playerLink":"/cfb/players/jaylon-scott-2.html","school_name":"North Carolina State","school_nameLink":"/cfb/schools/north-carolina-state/2021.html","tackles_solo":"1","tackles_assists":"2","tackles_total":"3","tackles_loss":"0.0","sacks":"0.0","def_int":"","def_int_yds":"","def_int_yds_per_int":"","def_int_td":"","pass_defended":"","fumbles_rec":"","fumbles_rec_yds":"","fumbles_rec_td":"","fumbles_forced":""},{"player":"Shyheim Battle","playerLink":"/cfb/players/shyheim-battle-1.html","school_name":"North Carolina State","school_nameLink":"/cfb/schools/north-carolina-state/2021.html","tackles_solo":"2","tackles_assists":"0","tackles_total":"2","tackles_loss":"0.0","sacks":"0.0","def_int":"","def_int_yds":"","def_int_yds_per_int":"","def_int_td":"","pass_defended":"","fumbles_rec":"","fumbles_rec_yds":"","fumbles_rec_td":"","fumbles_forced":""},{"player":"Savion Jackson","playerLink":"/cfb/players/savion-jackson-1.html","school_name":"North Carolina State","school_nameLink":"/cfb/schools/north-carolina-state/2021.html","tackles_solo":"1","tackles_assists":"1","tackles_total":"2","tackles_loss":"0.0","sacks":"0.0","def_int":"","def_int_yds":"","def_int_yds_per_int":"","def_int_td":"","pass_defended":"","fumbles_rec":"","fumbles_rec_yds":"","fumbles_rec_td":"","fumbles_forced":""},{"player":"Daniel Joseph","playerLink":"/cfb/players/daniel-joseph-2.html","school_name":"North Carolina State","school_nameLink":"/cfb/schools/north-carolina-state/2021.html","tackles_solo":"0","tackles_assists":"2","tackles_total":"2","tackles_loss":"0.0","sacks":"0.0","def_int":"","def_int_yds":"","def_int_yds_per_int":"","def_int_td":"","pass_defended":"","fumbles_rec":"","fumbles_rec_yds":"","fumbles_rec_td":"","fumbles_forced":""},{"player":"Tyler Baker-Williams","playerLink":"/cfb/players/tyler-baker-williams-1.html","school_name":"North Carolina State","school_nameLink":"/cfb/schools/north-carolina-state/2021.html","tackles_solo":"1","tackles_assists":"0","tackles_total":"1","tackles_loss":"0.0","sacks":"0.0","def_int":"","def_int_yds":"","def_int_yds_per_int":"","def_int_td":"","pass_defended":"1","fumbles_rec":"","fumbles_rec_yds":"","fumbles_rec_td":"","fumbles_forced":""},{"player":"Keyon Lesane","playerLink":"/cfb/players/keyon-lesane-1.html","school_name":"North Carolina State","school_nameLink":"/cfb/schools/north-carolina-state/2021.html","tackles_solo":"0","tackles_assists":"1","tackles_total":"1","tackles_loss":"0.0","sacks":"0.0","def_int":"","def_int_yds":"","def_int_yds_per_int":"","def_int_td":"","pass_defended":"","fumbles_rec":"","fumbles_rec_yds":"","fumbles_rec_td":"","fumbles_forced":""},{"player":"Davin Vann","playerLink":"/cfb/players/davin-vann-1.html","school_name":"North Carolina State","school_nameLink":"/cfb/schools/north-carolina-state/2021.html","tackles_solo":"0","tackles_assists":"1","tackles_total":"1","tackles_loss":"0.5","sacks":"0.5","def_int":"","def_int_yds":"","def_int_yds_per_int":"","def_int_td":"","pass_defended":"","fumbles_rec":"","fumbles_rec_yds":"","fumbles_rec_td":"","fumbles_forced":""},{"player":"Kameron Walker","playerLink":"/cfb/players/kameron-walker-1.html","school_name":"North Carolina State","school_nameLink":"/cfb/schools/north-carolina-state/2021.html","tackles_solo":"0","tackles_assists":"1","tackles_total":"1","tackles_loss":"0.0","sacks":"0.0","def_int":"","def_int_yds":"","def_int_yds_per_int":"","def_int_td":"","pass_defended":"","fumbles_rec":"","fumbles_rec_yds":"","fumbles_rec_td":"","fumbles_forced":""}]