[{"ranker":"1","player":"Billy Myers","playerLink":"/cfb/players/billy-myers-1.html","g":"11","def_int":"3","def_int_yds":"9","def_int_yds_per_int":"3.0","def_int_td":"0","pass_defended":""},{"ranker":"2","player":"Carter Wiley","playerLink":"/cfb/players/carter-wiley-1.html","g":"11","def_int":"3","def_int_yds":"15","def_int_yds_per_int":"5.0","def_int_td":"0","pass_defended":""},{"ranker":"3","player":"Jamel Agemy","playerLink":"/cfb/players/jamel-agemy-1.html","g":"11","def_int":"2","def_int_yds":"8","def_int_yds_per_int":"4.0","def_int_td":"0","pass_defended":""},{"ranker":"4","player":"Mitch Dove","playerLink":"/cfb/players/mitch-dove-1.html","g":"11","def_int":"2","def_int_yds":"15","def_int_yds_per_int":"7.5","def_int_td":"0","pass_defended":""},{"ranker":"5","player":"Randy Cockrell","playerLink":"/cfb/players/randy-cockrell-1.html","g":"11","def_int":"1","def_int_yds":"18","def_int_yds_per_int":"18.0","def_int_td":"0","pass_defended":""},{"ranker":"6","player":"Paul Nelson","playerLink":"/cfb/players/paul-nelson-1.html","g":"11","def_int":"1","def_int_yds":"9","def_int_yds_per_int":"9.0","def_int_td":"0","pass_defended":""},{"ranker":"7","player":"Scott Rice","playerLink":"/cfb/players/scott-rice-1.html","g":"11","def_int":"1","def_int_yds":"40","def_int_yds_per_int":"40.0","def_int_td":"0","pass_defended":""},{"ranker":"8","player":"Curtis Taliaferro","playerLink":"/cfb/players/curtis-taliaferro-2.html","g":"11","def_int":"1","def_int_yds":"0","def_int_yds_per_int":"0.0","def_int_td":"0","pass_defended":""},{"ranker":"9","player":"Lawrence White","playerLink":"/cfb/players/lawrence-white-1.html","g":"11","def_int":"1","def_int_yds":"10","def_int_yds_per_int":"10.0","def_int_td":"0","pass_defended":""}]