[{"ranker":"1","player":"Mike Mason","playerLink":"/cfb/players/mike-mason-1.html","g":"12","kick_ret":"22","kick_ret_yds":"508","kick_ret_yds_per_ret":"23.1","kick_ret_td":"0","punt_ret":"","punt_ret_yds":"","punt_ret_yds_per_ret":"","punt_ret_td":""},{"ranker":"2","player":"Trimane Goddard","playerLink":"/cfb/players/trimane-goddard-1.html","g":"11","kick_ret":"9","kick_ret_yds":"175","kick_ret_yds_per_ret":"19.4","kick_ret_td":"0","punt_ret":"","punt_ret_yds":"","punt_ret_yds_per_ret":"","punt_ret_td":""},{"ranker":"3","player":"Wallace Wright","playerLink":"/cfb/players/wallace-wright-1.html","g":"12","kick_ret":"8","kick_ret_yds":"135","kick_ret_yds_per_ret":"16.9","kick_ret_td":"0","punt_ret":"","punt_ret_yds":"","punt_ret_yds_per_ret":"","punt_ret_td":""},{"ranker":"4","player":"Del Roberts","playerLink":"/cfb/players/del-roberts-1.html","g":"5","kick_ret":"7","kick_ret_yds":"152","kick_ret_yds_per_ret":"21.7","kick_ret_td":"0","punt_ret":"1","punt_ret_yds":"7","punt_ret_yds_per_ret":"7.0","punt_ret_td":"0"},{"ranker":"5","player":"Chad Scott","playerLink":"/cfb/players/chad-scott-1.html","g":"11","kick_ret":"3","kick_ret_yds":"36","kick_ret_yds_per_ret":"12.0","kick_ret_td":"0","punt_ret":"","punt_ret_yds":"","punt_ret_yds_per_ret":"","punt_ret_td":""},{"ranker":"6","player":"Jarwarski Pollock","playerLink":"/cfb/players/jarwarski-pollock-1.html","g":"12","kick_ret":"","kick_ret_yds":"","kick_ret_yds_per_ret":"","kick_ret_td":"","punt_ret":"19","punt_ret_yds":"160","punt_ret_yds_per_ret":"8.4","punt_ret_td":"0"},{"ranker":"7","player":"Quinton Person","playerLink":"/cfb/players/quinton-person-1.html","g":"8","kick_ret":"","kick_ret_yds":"","kick_ret_yds_per_ret":"","kick_ret_td":"","punt_ret":"4","punt_ret_yds":"27","punt_ret_yds_per_ret":"6.8","punt_ret_td":"0"},{"ranker":"8","player":"Tom O'Leary","playerLink":"/cfb/players/tom-oleary-1.html","g":"6","kick_ret":"","kick_ret_yds":"","kick_ret_yds_per_ret":"","kick_ret_td":"","punt_ret":"1","punt_ret_yds":"16","punt_ret_yds_per_ret":"16.0","punt_ret_td":"0"},{"ranker":"9","player":"Mahlon Carey","playerLink":"/cfb/players/mahlon-carey-1.html","g":"12","kick_ret":"","kick_ret_yds":"","kick_ret_yds_per_ret":"","kick_ret_td":"","punt_ret":"1","punt_ret_yds":"9","punt_ret_yds_per_ret":"9.0","punt_ret_td":"0"},{"ranker":"10","player":"Daunte Fields","playerLink":"/cfb/players/daunte-fields-1.html","g":"8","kick_ret":"","kick_ret_yds":"","kick_ret_yds_per_ret":"","kick_ret_td":"","punt_ret":"1","punt_ret_yds":"-14","punt_ret_yds_per_ret":"-14.0","punt_ret_td":"0"},{"ranker":"11","player":"D.J. Walker","playerLink":"/cfb/players/dj-walker-1.html","g":"11","kick_ret":"","kick_ret_yds":"","kick_ret_yds_per_ret":"","kick_ret_td":"","punt_ret":"","punt_ret_yds":"1","punt_ret_yds_per_ret":"","punt_ret_td":"1"}]