[{"player":"Dylan Hopkins","playerLink":"/cfb/players/dylan-hopkins-1.html","school_name":"UAB","school_nameLink":"/cfb/schools/alabama-birmingham/2021.html","pass_cmp":"13","pass_att":"18","pass_cmp_pct":"72.2","pass_yds":"250","pass_yds_per_att":"13.9","adj_pass_yds_per_att":"13.9","pass_td":"0","pass_int":"0","pass_rating":"188.9"},{"header_passing":"Passing"},{"player":"Player","school_name":"School","pass_cmp":"Cmp","pass_att":"Att","pass_cmp_pct":"Pct","pass_yds":"Yds","pass_yds_per_att":"Y/A","adj_pass_yds_per_att":"AY/A","pass_td":"TD","pass_int":"Int","pass_rating":"Rate"},{"player":"Grant Wells","playerLink":"/cfb/players/grant-wells-1.html","school_name":"Marshall","school_nameLink":"/cfb/schools/marshall/2021.html","pass_cmp":"22","pass_att":"39","pass_cmp_pct":"56.4","pass_yds":"232","pass_yds_per_att":"5.9","adj_pass_yds_per_att":"5.8","pass_td":"2","pass_int":"1","pass_rating":"118.2"}]