[{"ranker":"1","player":"Alonzo Harris","playerLink":"/cfb/players/alonzo-harris-2.html","g":"13","td_rush":"14","td_rec":"","td_def_int":"","td_fumbles_rec":"","td_punt_ret":"","td_kick_ret":"","td_other":"","td_total":"14","xpm":"","fgm":"","two_pt_md":"","safety_md":"","points":"84"},{"ranker":"2","player":"Stephen Brauchle","playerLink":"/cfb/players/stephen-brauchle-1.html","g":"12","td_rush":"","td_rec":"","td_def_int":"","td_fumbles_rec":"","td_punt_ret":"","td_kick_ret":"","td_other":"","td_total":"","xpm":"52","fgm":"8","two_pt_md":"","safety_md":"","points":"76"},{"ranker":"3","player":"Elijah McGuire","playerLink":"/cfb/players/elijah-mcguire-1.html","g":"13","td_rush":"8","td_rec":"3","td_def_int":"","td_fumbles_rec":"","td_punt_ret":"","td_kick_ret":"","td_other":"","td_total":"11","xpm":"","fgm":"","two_pt_md":"","safety_md":"","points":"66"},{"ranker":"4","player":"Jamal Robinson","playerLink":"/cfb/players/jamal-robinson-3.html","g":"13","td_rush":"","td_rec":"8","td_def_int":"","td_fumbles_rec":"","td_punt_ret":"","td_kick_ret":"","td_other":"","td_total":"8","xpm":"","fgm":"","two_pt_md":"1","safety_md":"","points":"50"},{"ranker":"5","player":"Terrance Broadway","playerLink":"/cfb/players/terrance-broadway-1.html","g":"12","td_rush":"8","td_rec":"","td_def_int":"","td_fumbles_rec":"","td_punt_ret":"","td_kick_ret":"","td_other":"","td_total":"8","xpm":"","fgm":"","two_pt_md":"","safety_md":"","points":"48"},{"ranker":"6","player":"Darryl Surgent","playerLink":"/cfb/players/darryl-surgent-1.html","g":"13","td_rush":"","td_rec":"5","td_def_int":"","td_fumbles_rec":"","td_punt_ret":"1","td_kick_ret":"1","td_other":"","td_total":"7","xpm":"","fgm":"","two_pt_md":"","safety_md":"","points":"42"},{"ranker":"7","player":"Torrey Pierce","playerLink":"/cfb/players/torrey-pierce-1.html","g":"10","td_rush":"2","td_rec":"","td_def_int":"","td_fumbles_rec":"","td_punt_ret":"","td_kick_ret":"","td_other":"","td_total":"2","xpm":"","fgm":"","two_pt_md":"","safety_md":"","points":"12"},{"ranker":"8","player":"Jacob Maxwell","playerLink":"/cfb/players/jacob-maxwell-1.html","g":"7","td_rush":"","td_rec":"2","td_def_int":"","td_fumbles_rec":"","td_punt_ret":"","td_kick_ret":"","td_other":"","td_total":"2","xpm":"","fgm":"","two_pt_md":"","safety_md":"","points":"12"},{"ranker":"9","player":"James Butler","playerLink":"/cfb/players/james-butler-2.html","g":"10","td_rush":"","td_rec":"1","td_def_int":"","td_fumbles_rec":"","td_punt_ret":"","td_kick_ret":"","td_other":"","td_total":"1","xpm":"","fgm":"","two_pt_md":"","safety_md":"","points":"6"},{"ranker":"10","player":"Justin Anderson","playerLink":"/cfb/players/justin-anderson-5.html","g":"12","td_rush":"","td_rec":"","td_def_int":"1","td_fumbles_rec":"","td_punt_ret":"","td_kick_ret":"","td_other":"","td_total":"1","xpm":"","fgm":"","two_pt_md":"","safety_md":"","points":"6"},{"ranker":"11","player":"Montrel Carter","playerLink":"/cfb/players/montrel-carter-1.html","g":"7","td_rush":"1","td_rec":"","td_def_int":"","td_fumbles_rec":"","td_punt_ret":"","td_kick_ret":"","td_other":"","td_total":"1","xpm":"","fgm":"","two_pt_md":"","safety_md":"","points":"6"},{"ranker":"12","player":"Ricky Johnson","playerLink":"/cfb/players/ricky-johnson-1.html","g":"5","td_rush":"","td_rec":"1","td_def_int":"","td_fumbles_rec":"","td_punt_ret":"","td_kick_ret":"","td_other":"","td_total":"1","xpm":"","fgm":"","two_pt_md":"","safety_md":"","points":"6"},{"ranker":"13","player":"Effrem Reed","playerLink":"/cfb/players/effrem-reed-1.html","g":"9","td_rush":"","td_rec":"1","td_def_int":"","td_fumbles_rec":"","td_punt_ret":"","td_kick_ret":"","td_other":"","td_total":"1","xpm":"","fgm":"","two_pt_md":"","safety_md":"","points":"6"},{"ranker":"14","player":"Corey Trim","playerLink":"/cfb/players/corey-trim-1.html","g":"12","td_rush":"","td_rec":"","td_def_int":"1","td_fumbles_rec":"","td_punt_ret":"","td_kick_ret":"","td_other":"","td_total":"1","xpm":"","fgm":"","two_pt_md":"","safety_md":"","points":"6"},{"ranker":"15","player":"Al-Damion Riles","playerLink":"/cfb/players/al-damion-riles-1.html","g":"13","td_rush":"","td_rec":"","td_def_int":"1","td_fumbles_rec":"","td_punt_ret":"","td_kick_ret":"","td_other":"","td_total":"1","xpm":"","fgm":"","two_pt_md":"","safety_md":"","points":"6"},{"ranker":"16","player":"Hunter Stover","playerLink":"/cfb/players/hunter-stover-1.html","g":"8","td_rush":"","td_rec":"","td_def_int":"","td_fumbles_rec":"","td_punt_ret":"","td_kick_ret":"","td_other":"","td_total":"","xpm":"2","fgm":"1","two_pt_md":"","safety_md":"","points":"5"},{"ranker":"17","player":"Jalen Nixon","playerLink":"/cfb/players/jalen-nixon-1.html","g":"3","td_rush":"","td_rec":"","td_def_int":"","td_fumbles_rec":"","td_punt_ret":"","td_kick_ret":"","td_other":"","td_total":"","xpm":"","fgm":"","two_pt_md":"1","safety_md":"","points":"2"}]