[{"ranker":"1","player":"Andrew Stein","playerLink":"/cfb/players/andrew-stein-1.html","g":"12","td_rush":"","td_rec":"","td_def_int":"","td_fumbles_rec":"","td_punt_ret":"","td_kick_ret":"","td_other":"","td_total":"","xpm":"27","fgm":"17","two_pt_md":"","safety_md":"","points":"78"},{"ranker":"2","player":"Frank Gore Jr.","playerLink":"/cfb/players/frank-gore-jr-1.html","g":"12","td_rush":"10","td_rec":"3","td_def_int":"","td_fumbles_rec":"","td_punt_ret":"","td_kick_ret":"","td_other":"","td_total":"13","xpm":"","fgm":"","two_pt_md":"","safety_md":"","points":"78"},{"ranker":"3","player":"Jakarius Caston","playerLink":"/cfb/players/jakarius-caston-1.html","g":"12","td_rush":"1","td_rec":"6","td_def_int":"","td_fumbles_rec":"","td_punt_ret":"","td_kick_ret":"1","td_other":"","td_total":"8","xpm":"","fgm":"","two_pt_md":"","safety_md":"","points":"48"},{"ranker":"4","player":"Latreal Jones","playerLink":"/cfb/players/latreal-jones-1.html","g":"12","td_rush":"","td_rec":"3","td_def_int":"","td_fumbles_rec":"","td_punt_ret":"","td_kick_ret":"","td_other":"","td_total":"3","xpm":"","fgm":"","two_pt_md":"","safety_md":"","points":"18"},{"ranker":"5","player":"Tiaquelin Mims","playerLink":"/cfb/players/tiaquelin-mims-1.html","g":"12","td_rush":"","td_rec":"2","td_def_int":"","td_fumbles_rec":"","td_punt_ret":"1","td_kick_ret":"","td_other":"","td_total":"3","xpm":"","fgm":"","two_pt_md":"","safety_md":"","points":"18"},{"ranker":"6","player":"Rodrigues Clark","playerLink":"/cfb/players/rodrigues-clark-1.html","g":"10","td_rush":"2","td_rec":"","td_def_int":"","td_fumbles_rec":"","td_punt_ret":"","td_kick_ret":"","td_other":"","td_total":"2","xpm":"","fgm":"","two_pt_md":"","safety_md":"","points":"12"},{"ranker":"7","player":"Billy Wiles","playerLink":"/cfb/players/billy-wiles-1.html","g":"11","td_rush":"1","td_rec":"","td_def_int":"","td_fumbles_rec":"","td_punt_ret":"","td_kick_ret":"","td_other":"","td_total":"1","xpm":"","fgm":"","two_pt_md":"","safety_md":"","points":"6"},{"ranker":"8","player":"Ethan Crawford","playerLink":"/cfb/players/ethan-crawford-2.html","g":"6","td_rush":"1","td_rec":"","td_def_int":"","td_fumbles_rec":"","td_punt_ret":"","td_kick_ret":"","td_other":"","td_total":"1","xpm":"","fgm":"","two_pt_md":"","safety_md":"","points":"6"},{"ranker":"9","player":"Kenyon Clay","playerLink":"/cfb/players/kenyon-clay-1.html","g":"11","td_rush":"1","td_rec":"","td_def_int":"","td_fumbles_rec":"","td_punt_ret":"","td_kick_ret":"","td_other":"","td_total":"1","xpm":"","fgm":"","two_pt_md":"","safety_md":"","points":"6"},{"ranker":"10","player":"Tyquan Henderson","playerLink":"/cfb/players/tyquan-henderson-1.html","g":"12","td_rush":"","td_rec":"1","td_def_int":"","td_fumbles_rec":"","td_punt_ret":"","td_kick_ret":"","td_other":"","td_total":"1","xpm":"","fgm":"","two_pt_md":"","safety_md":"","points":"6"},{"ranker":"11","player":"Connor Gibbs","playerLink":"/cfb/players/connor-gibbs-1.html","g":"12","td_rush":"","td_rec":"","td_def_int":"","td_fumbles_rec":"","td_punt_ret":"","td_kick_ret":"","td_other":"","td_total":"","xpm":"2","fgm":"","two_pt_md":"","safety_md":"","points":"2"}]